odoo/addons/l10n_it_website_portal_ipa/README.rst
odoo/addons/l10n_it_website_portal_ipa/__init__.py
odoo/addons/l10n_it_website_portal_ipa/__manifest__.py
odoo/addons/l10n_it_website_portal_ipa/controllers/__init__.py
odoo/addons/l10n_it_website_portal_ipa/controllers/main.py
odoo/addons/l10n_it_website_portal_ipa/i18n/it.po
odoo/addons/l10n_it_website_portal_ipa/i18n/l10n_it_website_portal_ipa.pot
odoo/addons/l10n_it_website_portal_ipa/readme/DESCRIPTION.md
odoo/addons/l10n_it_website_portal_ipa/static/description/icon.png
odoo/addons/l10n_it_website_portal_ipa/static/description/index.html
odoo/addons/l10n_it_website_portal_ipa/static/src/js/l10n_it_website_portal_ipa.js
odoo/addons/l10n_it_website_portal_ipa/views/portal_templates.xml
odoo_addon_l10n_it_website_portal_ipa-16.0.1.0.1.4.dist-info/METADATA
odoo_addon_l10n_it_website_portal_ipa-16.0.1.0.1.4.dist-info/WHEEL
odoo_addon_l10n_it_website_portal_ipa-16.0.1.0.1.4.dist-info/top_level.txt
odoo_addon_l10n_it_website_portal_ipa-16.0.1.0.1.4.dist-info/RECORD
